datacraft_xeger/__init__.py
datacraft_xeger/suppliers.py
datacraft_xeger-0.1.1.dist-info/LICENSE
datacraft_xeger-0.1.1.dist-info/METADATA
datacraft_xeger-0.1.1.dist-info/WHEEL
datacraft_xeger-0.1.1.dist-info/entry_points.txt
datacraft_xeger-0.1.1.dist-info/top_level.txt
datacraft_xeger-0.1.1.dist-info/RECORD
