Metadata-Version: 2.1
Name: datacraft-xeger
Version: 0.1.1
Summary: Custom xeger type extensions for datacraft package
Home-page: https://github.com/bbux-dev/datacraft-xeger
Author: Brian Buxton
Author-email: bbux-dev@gmail.com
License: MIT
License-File: LICENSE
Requires-Dist: datacraft (>=0.3.1)
Requires-Dist: rstr
Provides-Extra: all
Requires-Dist: pytest (>=6.2.2) ; extra == 'all'
Requires-Dist: pycodestyle ; extra == 'all'
Requires-Dist: pytest-cov ; extra == 'all'
Provides-Extra: test
Requires-Dist: pytest (>=6.2.2) ; extra == 'test'
Requires-Dist: pycodestyle ; extra == 'test'
Requires-Dist: pytest-cov ; extra == 'test'
